License.txt
README.md
setup.py
summers_pack/__init__.py
summers_pack.egg-info/PKG-INFO
summers_pack.egg-info/SOURCES.txt
summers_pack.egg-info/dependency_links.txt
summers_pack.egg-info/top_level.txt