Metadata-Version: 2.1
Name: summers_pack
Version: 0.0.1
Summary: For doing calculations like Addition, Multiplication and Subtraction
Author: Ansh Gupta
Author-email: Ansh.Gupta@iiitb.ac.in
License: MIT
Classifier: Programming Language :: Python :: 3
Classifier: License :: OSI Approved :: MIT License
Classifier: Operating System :: OS Independent
Requires-Python: >=3.6
License-File: License.txt
